{
	"format_version": "1.8.0",
	"animations": {
		"animation.plague_dog.spawn": {
			"animation_length": 3.45833,
			"bones": {
				"All": {
					"rotation": {
						"1.625": [
							0,
							0,
							-2.5
						],
						"2.125": [
							0,
							0,
							-12.5
						],
						"3.4583": [
							12.25713,
							2.3415,
							-11.4634
						]
					},
					"position": {
						"0.0": [
							0,
							-22,
							0
						],
						"0.1667": [
							0,
							-18,
							0
						],
						"0.625": [
							0,
							-18,
							0
						],
						"0.9167": [
							0,
							-16,
							0
						],
						"1.1667": [
							0,
							-16,
							0
						],
						"1.625": [
							1,
							-12,
							0
						],
						"2.125": [
							2,
							-11,
							0
						],
						"2.625": [
							2,
							-11,
							0
						],
						"3.4583": [
							2,
							0,
							0
						]
					},
					"scale": 1
				},
				"hip": {
					"rotation": {
						"1.1667": [
							0,
							0,
							0
						],
						"2.1667": [
							-0.32856,
							-0.80982,
							-0.15538
						],
						"2.625": [
							-0.4642,
							-0.74046,
							9.8453
						],
						"3.4167": [
							-52.9642,
							-0.74046,
							9.8453
						]
					},
					"position": [
						0,
						0,
						0
					]
				},
				"Abdomen": {
					"rotation": {
						"0.0": [
							0,
							0,
							0
						],
						"2.625": [
							0,
							0,
							0
						],
						"3.4167": [
							-12.5,
							0,
							0
						]
					}
				},
				"Chest": {
					"rotation": {
						"0.0": [
							-6.35215,
							2.31234,
							-7.20174
						],
						"0.1667": [
							-72.5,
							0,
							0
						],
						"1.1667": [
							-72.5,
							0,
							0
						],
						"1.625": [
							-10,
							0,
							0
						],
						"2.625": [
							-10,
							0,
							0
						],
						"3.4167": [
							-24.86486,
							-0.991,
							1.21861
						]
					}
				},
				"Neck": {
					"rotation": {
						"0.0": [
							0,
							0,
							0
						],
						"0.1667": [
							0,
							0,
							0
						],
						"0.625": [
							62.5,
							0,
							0
						],
						"0.9167": [
							75,
							0,
							0
						],
						"1.1667": [
							75,
							0,
							0
						],
						"1.625": [
							7.5,
							0,
							0
						],
						"2.625": [
							7.5,
							0,
							0
						],
						"3.4167": [
							72.5,
							0,
							0
						]
					}
				},
				"Head": {
					"rotation": {
						"0.0": [
							0,
							0,
							0
						],
						"0.1667": [
							0,
							0,
							0
						],
						"0.4167": [
							-25.91,
							0,
							0
						],
						"0.625": [
							7.5,
							0,
							0
						],
						"0.9167": [
							0.03154,
							0.15053,
							-0.68081
						],
						"1.625": [
							7.53154,
							0.15053,
							-0.68081
						],
						"2.125": [
							7.38731,
							-1.47863,
							11.71382
						],
						"2.625": [
							7.5395,
							2.62895,
							-0.35289
						]
					}
				},
				"Head2": {
					"rotation": [
						0,
						0,
						0
					]
				},
				"RightArm": {
					"rotation": {
						"0.625": [
							0,
							0,
							0
						],
						"0.9167": [
							-58.97631,
							17.49722,
							29.96374
						],
						"1.1667": [
							-35.5867,
							11.72145,
							41.15088
						],
						"1.625": [
							-107.36465,
							36.65499,
							6.72261
						],
						"2.125": [
							-105.27483,
							39.39525,
							22.22701
						],
						"2.625": [
							-92.77483,
							39.39525,
							22.22701
						],
						"3.4167": [
							81.0986,
							-13.7389,
							5.1421
						]
					}
				},
				"RightForeArm": {
					"rotation": {
						"0.625": [
							0,
							0,
							0
						],
						"0.7917": [
							10.41,
							0,
							0
						],
						"0.9167": [
							-16.79,
							0,
							0
						],
						"1.0417": [
							-13.39,
							0,
							0
						],
						"1.1667": [
							45,
							0,
							0
						],
						"2.625": [
							45,
							0,
							0
						],
						"3.4167": [
							-72.5,
							0,
							0
						]
					}
				},
				"RightHand": {
					"rotation": {
						"0.625": [
							0,
							0,
							0
						],
						"0.7917": [
							21.35,
							0,
							0
						],
						"1.1667": [
							-20,
							0,
							0
						],
						"2.625": [
							-20.15874,
							7.04533,
							-2.57816
						],
						"3.4167": [
							49.84126,
							7.04533,
							-2.57816
						]
					}
				},
				"LeftArm": {
					"rotation": {
						"0.625": [
							0,
							0,
							0
						],
						"0.7917": [
							-50.87416,
							-5.35381,
							-28.29369
						],
						"0.9167": [
							-60.27125,
							-12.59021,
							-21.60449
						],
						"1.1667": [
							-35.27125,
							-12.59021,
							-21.60449
						],
						"1.625": [
							-99.89259,
							-28.51254,
							-8.61576
						],
						"2.125": [
							-90.38321,
							-28.92621,
							2.78159
						],
						"2.625": [
							-102.88321,
							-28.92621,
							2.78159
						],
						"3.4167": [
							78.73961,
							-2.00938,
							-3.13133
						]
					}
				},
				"LeftForeArm": {
					"rotation": {
						"0.625": [
							0,
							0,
							0
						],
						"0.7917": [
							60,
							0,
							0
						],
						"0.9167": [
							-12.5,
							0,
							0
						],
						"1.0417": [
							-20,
							0,
							0
						],
						"1.1667": [
							32.5,
							0,
							0
						],
						"2.625": [
							32.5,
							0,
							0
						],
						"3.4167": [
							-68.96338,
							16.18059,
							0.75336
						]
					}
				},
				"LeftHand": {
					"rotation": {
						"0.625": [
							0,
							0,
							0
						],
						"0.7917": [
							-25,
							0,
							0
						],
						"1.1667": [
							-15,
							0,
							0
						],
						"2.625": [
							-10,
							0,
							0
						],
						"3.4167": [
							25,
							0,
							0
						]
					}
				},
				"Tail": {
					"rotation": {
						"1.1667": [
							-25,
							0,
							0
						],
						"1.4167": [
							17.5,
							0,
							0
						],
						"1.625": [
							-25,
							0,
							0
						]
					}
				},
				"Tail2": {
					"rotation": {
						"1.1667": [
							-25,
							0,
							0
						],
						"1.4167": [
							17.5,
							0,
							0
						],
						"1.625": [
							-25,
							0,
							0
						]
					}
				},
				"RightLeg": {
					"rotation": {
						"1.1667": [
							0,
							0,
							0
						],
						"1.625": [
							0,
							0,
							0
						],
						"2.125": [
							1.35353,
							16.45457,
							7.40834
						],
						"2.625": [
							-128.47332,
							24.92476,
							-0.38465
						],
						"3.4167": [
							-7.44436,
							6.04911,
							18.74234
						]
					},
					"position": {
						"2.625": [
							0,
							0,
							0
						],
						"2.9167": [
							0,
							2,
							0
						],
						"3.1667": [
							0,
							3,
							0
						],
						"3.4167": [
							0,
							0,
							0
						]
					}
				},
				"bone": {
					"rotation": {
						"1.1667": [
							0,
							0,
							0
						],
						"1.625": [
							0,
							0,
							0
						],
						"2.125": [
							0,
							0,
							0
						],
						"2.625": [
							17.43914,
							-0.4881,
							-0.2604
						],
						"3.4167": [
							-0.06086,
							-0.4881,
							-0.2604
						]
					}
				},
				"bone2": {
					"rotation": {
						"1.1667": [
							0,
							0,
							0
						],
						"1.625": [
							0,
							0,
							0
						],
						"2.125": [
							0,
							0,
							0
						],
						"2.625": [
							32.5,
							0,
							0
						]
					}
				},
				"RightFoot": {
					"rotation": {
						"1.1667": [
							0,
							0,
							0
						],
						"1.625": [
							0,
							0,
							0
						],
						"2.125": [
							0,
							0,
							0
						],
						"2.625": [
							74.63726,
							-9.68469,
							2.531
						],
						"3.4167": [
							-40.36274,
							-9.68469,
							2.531
						]
					}
				},
				"LeftLeg": {
					"rotation": {
						"1.1667": [
							0,
							0,
							0
						],
						"1.625": [
							0,
							0,
							0
						],
						"2.125": [
							-106.55952,
							-25.35192,
							5.66113
						],
						"2.625": [
							-106.55952,
							-25.35192,
							5.66113
						],
						"3.4167": [
							-18.84336,
							-0.98943,
							6.25782
						]
					},
					"position": {
						"2.625": [
							0,
							0,
							0
						],
						"2.9167": [
							0,
							1,
							0
						],
						"3.1667": [
							0,
							1.5,
							0
						],
						"3.4167": [
							0,
							0,
							0
						]
					}
				},
				"bone3": {
					"rotation": {
						"1.1667": [
							0,
							0,
							0
						],
						"1.625": [
							0,
							0,
							0
						],
						"2.125": [
							12.5,
							0,
							0
						],
						"2.625": [
							12.5,
							0,
							0
						],
						"3.4167": [
							-22.5,
							0,
							0
						]
					}
				},
				"bone4": {
					"rotation": {
						"1.1667": [
							0,
							0,
							0
						],
						"1.625": [
							0,
							0,
							0
						],
						"2.125": [
							21.69493,
							1.16419,
							6.11435
						],
						"2.625": [
							21.69493,
							1.16419,
							6.11435
						],
						"3.4167": [
							31.69493,
							1.16419,
							6.11435
						]
					}
				},
				"LeftFoot": {
					"rotation": {
						"1.1667": [
							0,
							0,
							0
						],
						"1.625": [
							0,
							0,
							0
						],
						"2.125": [
							74.49591,
							-14.47751,
							3.96713
						],
						"2.625": [
							74.49591,
							-14.47751,
							3.96713
						],
						"3.4167": [
							-2.91758,
							-4.49079,
							3.4441
						]
					}
				},
				"outcast": {
					"position": [
						0,
						-100,
						7
					],
					"scale": 0
				}
			}
		},
		"animation.plague_dog.static": {
			"loop": true,
			"animation_length": 3.4,
			"bones": {
				"RightFoot": {
					"rotation": [
						12.5,
						0,
						0
					]
				},
				"RightLeg": {
					"rotation": [
						52.5,
						0,
						0
					]
				},
				"bone": {
					"rotation": [
						-50,
						0,
						0
					]
				},
				"bone2": {
					"rotation": [
						-15.12734,
						-2.3069,
						-1.27736
					]
				},
				"hip": {
					"rotation": [
						-40,
						0,
						0
					]
				},
				"Abdomen": {
					"rotation": {
						"0.0": [
							-7.5,
							0,
							0
						],
						"1.48": [
							-2.5,
							0,
							0
						],
						"3.4": [
							-7.5,
							0,
							0
						]
					},
					"scale": {
						"0.0": [
							1,
							1,
							1
						],
						"1.48": [
							1.1,
							1.1,
							1.1
						],
						"3.4": [
							1,
							1,
							1
						]
					}
				},
				"Chest": {
					"rotation": [
						-20,
						0,
						0
					],
					"position": {
						"0.0": [
							0,
							0,
							0
						],
						"1.48": [
							0,
							0,
							0
						],
						"3.4": [
							0,
							0,
							0
						]
					},
					"scale": {
						"0.0": [
							1,
							1,
							1
						],
						"1.48": [
							0.9,
							0.9,
							0.9
						],
						"3.4": [
							1,
							1,
							1
						]
					}
				},
				"Tail": {
					"rotation": {
						"0.0": [
							42.5,
							0,
							0
						],
						"1.48": [
							0.40057,
							-1.10121,
							-4.91669
						],
						"3.4": [
							42.5,
							0,
							0
						]
					}
				},
				"Tail2": {
					"rotation": {
						"0.0": [
							32.5,
							0,
							0
						],
						"1.0": [
							30.27,
							0,
							0
						],
						"1.48": [
							-30,
							0,
							0
						],
						"2.92": [
							-25.25872,
							-6.24325,
							-4.00125
						],
						"3.4": [
							32.5,
							0,
							0
						]
					}
				},
				"RightHand": {
					"rotation": {
						"0.0": [
							45,
							0,
							0
						],
						"3.4": [
							45,
							0,
							0
						]
					}
				},
				"RightArm": {
					"rotation": [
						98.26511,
						-24.77164,
						-3.48303
					]
				},
				"RightForeArm": {
					"rotation": [
						-77.5,
						0,
						0
					]
				},
				"Finger": {
					"rotation": {
						"0.0": [
							-52.12711,
							28.93057,
							20.61737
						],
						"1.48": [
							-49.78251,
							33.65855,
							25.11351
						],
						"3.4": [
							-52.12711,
							28.93057,
							20.61737
						]
					}
				},
				"Finger3": {
					"rotation": {
						"0.0": [
							0,
							-65,
							-32.5
						],
						"1.48": [
							1.94227,
							-62.69809,
							-48.20447
						],
						"3.4": [
							0,
							-65,
							-32.5
						]
					}
				},
				"Finger2": {
					"rotation": {
						"0.0": [
							-72.5,
							0,
							0
						],
						"1.48": [
							-72.43726,
							-4.76804,
							-1.50701
						],
						"3.4": [
							-72.5,
							0,
							0
						]
					}
				},
				"Neck": {
					"rotation": [
						72.5,
						0,
						0
					]
				},
				"Head": {
					"rotation": {
						"0.0": [
							5,
							"math.clamp(q.target_y_rotation,-40,40)",
							0
						],
						"1.48": [
							-7.5,
							0,
							0
						],
						"3.4": [
							5,
							0,
							0
						]
					}
				},
				"Head2": {
					"rotation": {
						"0.0": [
							10.22343,
							-0.20442,
							0.74892
						],
						"1.48": [
							17.5149,
							1.07628,
							2.00926
						],
						"3.4": [
							10.22343,
							-0.20442,
							0.74892
						]
					}
				},
				"eitherEar": {
					"rotation": [
						-11.70092,
						19.3546,
						-32.00206
					]
				},
				"LeftArm": {
					"rotation": [
						79.52521,
						17.22575,
						-3.13388
					]
				},
				"LeftForeArm": {
					"rotation": [
						-60,
						0,
						0
					]
				},
				"LeftHand": {
					"rotation": [
						37.5,
						0,
						0
					]
				},
				"Finger4": {
					"rotation": {
						"0.0": [
							-35,
							0,
							-20
						],
						"1.48": [
							-34.89743,
							-2.86544,
							-24.09918
						],
						"3.4": [
							-35,
							0,
							-20
						]
					}
				},
				"Finger5": {
					"rotation": {
						"0.0": [
							-50,
							0,
							0
						],
						"1.48": [
							-49.8924,
							3.82821,
							3.21873
						],
						"3.4": [
							-50,
							0,
							0
						]
					}
				},
				"Finger6": {
					"rotation": {
						"0.0": [
							-17.5,
							50,
							32.5
						],
						"1.48": [
							-6.5566,
							51.04401,
							40.19501
						],
						"3.4": [
							-17.5,
							50,
							32.5
						]
					}
				},
				"eitherEar2": {
					"rotation": [
						0,
						0,
						25
					]
				},
				"language": {
					"rotation": [
						14.48557,
						-3.1004,
						0.45036
					]
				},
				"language2": {
					"rotation": [
						-7.5,
						0,
						0
					]
				},
				"outcast": {
					"position": [
						0,
						-100,
						7
					],
					"scale": 0
				}
			}
		},
		"animation.plague_dog.static_two": {
			"loop": true,
			"animation_length": 3.5,
			"bones": {
				"Abdomen": {
					"rotation": {
						"0.0": [
							-20,
							0,
							0
						],
						"1.7917": [
							-12.5,
							0,
							0
						],
						"3.5": [
							-20,
							0,
							0
						]
					}
				},
				"Chest": {
					"rotation": {
						"0.0": [
							10,
							0,
							0
						],
						"1.7917": [
							5,
							0,
							0
						],
						"3.5": [
							10,
							0,
							0
						]
					}
				},
				"Neck": {
					"rotation": {
						"0.0": [
							7.5,
							0,
							0
						],
						"1.7917": [
							5,
							0,
							0
						],
						"3.5": [
							7.5,
							0,
							0
						]
					}
				},
				"Head": {
					"rotation": {
						"0.0": [
							15,
							"math.clamp(q.target_y_rotation,-40,40)",
							0
						],
						"1.7917": [
							10,
							0,
							0
						],
						"3.5": [
							15,
							0,
							0
						]
					}
				},
				"Head2": {
					"rotation": [
						0,
						0,
						0
					]
				},
				"RightArm": {
					"rotation": [
						59.92617,
						0.35395,
						2.39523
					]
				},
				"RightForeArm": {
					"rotation": [
						-102.5,
						0,
						0
					]
				},
				"RightHand": {
					"rotation": [
						37.5,
						0,
						0
					]
				},
				"LeftArm": {
					"rotation": [
						55,
						0,
						0
					]
				},
				"LeftForeArm": {
					"rotation": [
						-95,
						0,
						0
					]
				},
				"LeftHand": {
					"rotation": [
						34.82843,
						2.29597,
						3.47912
					]
				},
				"Tail": {
					"rotation": {
						"0.0": [
							-24.85944,
							2.10049,
							-2.17268
						],
						"1.7917": [
							12.64056,
							2.10049,
							-2.17268
						],
						"3.5": [
							-24.85944,
							2.10049,
							-2.17268
						]
					}
				},
				"Tail2": {
					"rotation": {
						"0.0": [
							-32.5,
							0,
							0
						],
						"0.7917": [
							-39.3,
							0,
							0
						],
						"1.7917": [
							20,
							0,
							0
						],
						"2.7917": [
							24.27,
							0,
							0
						],
						"3.5": [
							-32.5,
							0,
							0
						]
					}
				},
				"outcast": {
					"position": [
						0,
						-100,
						7
					],
					"scale": 0
				}
			}
		},
		"animation.plague_dog.move": {
			"loop": true,
			"animation_length": 0.7917,
			"bones": {
				"Abdomen": {
					"rotation": {
						"0.0": [
							-15,
							0,
							0
						],
						"0.125": [
							-18.55046,
							-0.16442,
							0.34559
						],
						"0.2083": [
							-12.5841,
							-0.27404,
							0.57598
						],
						"0.3333": [
							-9.03364,
							-0.10962,
							0.23039
						],
						"0.4167": [
							-15,
							0,
							0
						],
						"0.5417": [
							-17,
							0,
							0
						],
						"0.625": [
							-10,
							0,
							0
						],
						"0.7083": [
							-7.5,
							0,
							0
						],
						"0.7917": [
							-15,
							0,
							0
						]
					}
				},
				"Chest": {
					"rotation": {
						"0.0": [
							-5,
							0,
							0
						],
						"0.25": [
							6.5,
							0,
							0
						],
						"0.4167": [
							-2.5,
							0,
							0
						],
						"0.5833": [
							3.89,
							0,
							0
						],
						"0.7917": [
							-5,
							0,
							0
						]
					}
				},
				"Neck": {
					"rotation": [
						5,
						0,
						0
					]
				},
				"Head": {
					"rotation": {
						"0.0": [
							23.25866,
							-1.62259,
							-3.33506
						],
						"0.125": [
							33.19059,
							-1.28473,
							-2.91555
						],
						"0.25": [
							3.12252,
							-0.94686,
							-2.49603
						],
						"0.3333": [
							-4.30941,
							-1.28473,
							-2.91555
						],
						"0.4167": [
							23.25866,
							-1.62259,
							-3.33506
						],
						"0.5": [
							31.82997,
							-1.76452,
							-3.96098
						],
						"0.625": [
							13.43694,
							-1.97741,
							-4.89986
						],
						"0.7083": [
							0.8478,
							-1.8,
							-4.11746
						],
						"0.7917": [
							23.25866,
							-1.62259,
							-3.33506
						]
					}
				},
				"RightArm": {
					"rotation": [
						57.5,
						0,
						0
					]
				},
				"RightForeArm": {
					"rotation": [
						-120,
						0,
						0
					]
				},
				"LeftArm": {
					"rotation": [
						70,
						0,
						0
					]
				},
				"LeftForeArm": {
					"rotation": [
						-127.5,
						0,
						0
					]
				},
				"RightLeg": {
					"rotation": {
						"0.0": [
							-17.5,
							0,
							0
						],
						"0.4167": [
							22.5,
							0,
							0
						],
						"0.625": [
							-27.22,
							0,
							0
						],
						"0.7917": [
							-17.5,
							0,
							0
						]
					}
				},
				"bone": {
					"rotation": {
						"0.0": [
							-35,
							0,
							0
						],
						"0.2083": [
							1.25,
							0,
							0
						],
						"0.4167": [
							-22.5,
							0,
							0
						],
						"0.625": [
							15.56,
							0,
							0
						],
						"0.7917": [
							-35,
							0,
							0
						]
					}
				},
				"bone2": {
					"rotation": {
						"0.0": [
							20,
							0,
							0
						],
						"0.2083": [
							4.05622,
							3.70316,
							1.14381
						],
						"0.4167": [
							42.5,
							0,
							0
						],
						"0.625": [
							-27.5,
							0,
							0
						],
						"0.7917": [
							20,
							0,
							0
						]
					}
				},
				"RightFoot": {
					"rotation": {
						"0.0": [
							32.5,
							0,
							0
						],
						"0.2083": [
							-8.59624,
							2.22182,
							-5.27986
						],
						"0.4167": [
							-44.69248,
							4.44365,
							-10.55971
						],
						"0.625": [
							40.69223,
							1.97495,
							-4.69321
						],
						"0.7917": [
							32.5,
							0,
							0
						]
					}
				},
				"LeftLeg": {
					"rotation": {
						"0.0": [
							35,
							0,
							0
						],
						"0.2083": [
							-40,
							0,
							0
						],
						"0.4167": [
							-10,
							0,
							0
						],
						"0.7917": [
							35,
							0,
							0
						]
					}
				},
				"bone3": {
					"rotation": {
						"0.0": [
							-22.5,
							0,
							0
						],
						"0.2083": [
							15,
							0,
							0
						],
						"0.4167": [
							-37.5,
							0,
							0
						],
						"0.625": [
							-4.17,
							0,
							0
						],
						"0.7917": [
							-22.5,
							0,
							0
						]
					}
				},
				"bone4": {
					"rotation": {
						"0.0": [
							5,
							0,
							0
						],
						"0.2083": [
							-37.5,
							0,
							0
						],
						"0.4167": [
							5,
							0,
							0
						],
						"0.625": [
							-15,
							0,
							0
						],
						"0.7917": [
							5,
							0,
							0
						]
					}
				},
				"LeftFoot": {
					"rotation": {
						"0.0": [
							-16.59558,
							-5.16852,
							0.26089
						],
						"0.2083": [
							65.30142,
							-4.47176,
							4.18317
						],
						"0.4167": [
							43.38548,
							-5.04363,
							0.39716
						],
						"0.625": [
							5.06267,
							-5.11301,
							0.32146
						],
						"0.7917": [
							-16.59558,
							-5.16852,
							0.26089
						]
					}
				},
				"hip": {
					"position": {
						"0.0": [
							0,
							0,
							0
						],
						"0.2083": [
							0,
							-1,
							0
						],
						"0.4167": [
							0,
							0,
							0
						],
						"0.625": [
							0,
							-1,
							0
						],
						"0.7917": [
							0,
							0,
							0
						]
					}
				},
				"Tail": {
					"rotation": {
						"0.0": [
							-15,
							0,
							0
						],
						"0.4167": [
							32.21603,
							1.63495,
							-2.8868
						],
						"0.7917": [
							-15,
							0,
							0
						]
					}
				},
				"Tail2": {
					"rotation": {
						"0.0": [
							-27.5,
							0,
							0
						],
						"0.25": [
							-36,
							0,
							0
						],
						"0.4167": [
							25,
							0,
							0
						],
						"0.625": [
							33.33,
							0,
							0
						],
						"0.7917": [
							-27.5,
							0,
							0
						]
					}
				},
				"Head2": {
					"rotation": {
						"0.0": [
							0,
							0,
							0
						],
						"0.125": [
							-3.09571,
							-0.84452,
							-0.9735
						],
						"0.2917": [
							20,
							0,
							0
						],
						"0.4167": [
							-2.5,
							0,
							0
						],
						"0.625": [
							18.69186,
							1.32264,
							1.92493
						],
						"0.7917": [
							0,
							0,
							0
						]
					}
				},
				"outcast": {
					"position": [
						0,
						-100,
						7
					],
					"scale": 0
				}
			}
		},
		"animation.plague_dog.eating": {
			"loop": true,
			"animation_length": 0.5417,
			"bones": {
				"hip": {
					"rotation": [
						-15,
						0,
						0
					],
					"position": {
						"0.0": [
							0,
							1,
							0
						],
						"0.2917": [
							0,
							0,
							0
						],
						"0.5417": [
							0,
							1,
							0
						]
					}
				},
				"Abdomen": {
					"rotation": {
						"0.0": [
							-17.5,
							0,
							0
						],
						"0.2917": [
							-10,
							0,
							0
						],
						"0.5417": [
							-17.5,
							0,
							0
						]
					}
				},
				"Chest": {
					"rotation": [
						35,
						0,
						0
					]
				},
				"Neck": {
					"rotation": {
						"0.0": [
							32.5,
							0,
							0
						],
						"0.125": [
							42.86,
							0,
							0
						],
						"0.2917": [
							27.5,
							0,
							0
						],
						"0.5417": [
							32.5,
							0,
							0
						]
					}
				},
				"Head": {
					"rotation": {
						"0.0": [
							28.48124,
							9.84655,
							-17.49524
						],
						"0.2917": [
							2.5,
							0,
							0
						],
						"0.375": [
							-5.83,
							0,
							0
						],
						"0.5417": [
							28.48124,
							9.84655,
							-17.49524
						]
					}
				},
				"Head2": {
					"rotation": {
						"0.0": [
							37.5,
							0,
							0
						],
						"0.2917": [
							10,
							0,
							0
						],
						"0.5417": [
							37.5,
							0,
							0
						]
					}
				},
				"RightArm": {
					"rotation": {
						"0.0": [
							44.86012,
							2.02219,
							18.95003
						],
						"0.2917": [
							17.36012,
							2.02219,
							18.95003
						],
						"0.5417": [
							44.86012,
							2.02219,
							18.95003
						]
					}
				},
				"RightForeArm": {
					"rotation": {
						"0.0": [
							-62.5,
							0,
							0
						],
						"0.2917": [
							-32.5,
							0,
							0
						],
						"0.5417": [
							-62.5,
							0,
							0
						]
					}
				},
				"RightHand": {
					"rotation": {
						"0.0": [
							14.64,
							0,
							0
						],
						"0.125": [
							-13.22,
							0,
							0
						],
						"0.2917": [
							2.14,
							0,
							0
						],
						"0.4167": [
							33.39,
							0,
							0
						],
						"0.5417": [
							14.64,
							0,
							0
						]
					}
				},
				"Finger": {
					"rotation": [
						0.57324,
						-0.69789,
						17.47337
					]
				},
				"Finger2": {
					"rotation": [
						-7.14235,
						0.66388,
						-56.99479
					],
					"position": [
						0,
						1,
						0
					]
				},
				"Finger3": {
					"rotation": [
						0.44742,
						-1.65758,
						-12.81031
					]
				},
				"LeftArm": {
					"rotation": {
						"0.0": [
							51.94284,
							7.6469,
							-13.83098
						],
						"0.2917": [
							23.52094,
							-8.53648,
							-26.45785
						],
						"0.5417": [
							51.94284,
							7.6469,
							-13.83098
						]
					}
				},
				"LeftForeArm": {
					"rotation": {
						"0.0": [
							-63.75885,
							-13.50906,
							16.61984
						],
						"0.2917": [
							-33.41838,
							-9.43236,
							11.16052
						],
						"0.5417": [
							-63.75885,
							-13.50906,
							16.61984
						]
					}
				},
				"LeftHand": {
					"rotation": {
						"0.0": [
							7.5,
							0,
							0
						],
						"0.125": [
							-17.5,
							0,
							0
						],
						"0.2917": [
							5,
							0,
							0
						],
						"0.4167": [
							26.25,
							0,
							0
						],
						"0.5417": [
							7.5,
							0,
							0
						]
					}
				},
				"Finger4": {
					"rotation": [
						0,
						0,
						-15
					]
				},
				"Finger5": {
					"rotation": [
						0,
						0,
						25
					]
				},
				"Finger6": {
					"rotation": [
						0,
						0,
						55
					],
					"position": [
						0,
						1,
						0
					]
				},
				"Tail": {
					"rotation": {
						"0.0": [
							-20,
							0,
							0
						],
						"0.2917": [
							12.31403,
							2.55812,
							-1.78652
						],
						"0.5417": [
							-20,
							0,
							0
						]
					}
				},
				"Tail2": {
					"rotation": {
						"0.0": [
							-25,
							0,
							0
						],
						"0.1667": [
							-26.79,
							0,
							0
						],
						"0.2917": [
							20,
							0,
							0
						],
						"0.4167": [
							22.5,
							0,
							0
						],
						"0.5417": [
							-25,
							0,
							0
						]
					}
				},
				"RightLeg": {
					"rotation": [
						0,
						32.5,
						0
					],
					"position": {
						"0.0": [
							0,
							0,
							0
						],
						"0.2917": [
							0,
							1,
							1
						],
						"0.5417": [
							0,
							0,
							0
						]
					}
				},
				"LeftLeg": {
					"rotation": [
						0,
						-40,
						0
					],
					"position": {
						"0.0": [
							0,
							0,
							0
						],
						"0.2917": [
							0,
							1,
							1
						],
						"0.5417": [
							0,
							0,
							0
						]
					}
				},
				"bone": {
					"rotation": {
						"0.0": [
							0,
							0,
							0
						],
						"0.2917": [
							-15,
							0,
							0
						],
						"0.5417": [
							0,
							0,
							0
						]
					}
				},
				"bone2": {
					"rotation": {
						"0.0": [
							0,
							0,
							0
						],
						"0.2917": [
							12.5,
							0,
							0
						],
						"0.5417": [
							0,
							0,
							0
						]
					}
				},
				"RightFoot": {
					"rotation": {
						"0.0": [
							0,
							0,
							0
						],
						"0.2917": [
							2.5,
							0,
							0
						],
						"0.5417": [
							0,
							0,
							0
						]
					}
				},
				"bone3": {
					"rotation": {
						"0.0": [
							0,
							0,
							0
						],
						"0.2917": [
							-20,
							0,
							0
						],
						"0.5417": [
							0,
							0,
							0
						]
					}
				},
				"bone4": {
					"rotation": {
						"0.0": [
							0,
							0,
							0
						],
						"0.2917": [
							9.89047,
							1.23455,
							0.41962
						],
						"0.5417": [
							0,
							0,
							0
						]
					}
				},
				"LeftFoot": {
					"rotation": {
						"0.0": [
							0,
							0,
							0
						],
						"0.2917": [
							10,
							0,
							0
						],
						"0.5417": [
							0,
							0,
							0
						]
					}
				},
				"waist": {
					"rotation": {
						"0.0": [
							0,
							90,
							90
						],
						"0.1667": [
							0,
							90,
							90
						]
					},
					"position": {
						"0.0": [
							-16,
							2,
							-10
						],
						"0.0833": [
							-16,
							3,
							-10
						],
						"0.1667": [
							-16,
							2,
							-10
						]
					}
				},
				"body": {
					"rotation": {
						"0.0": [
							0,
							0,
							0
						],
						"0.0833": [
							-17.5,
							0,
							0
						],
						"0.1667": [
							0,
							0,
							0
						]
					},
					"position": {
						"0.0": [
							0,
							0,
							0
						],
						"0.0833": [
							0,
							0,
							2
						],
						"0.1667": [
							0,
							0,
							0
						]
					}
				},
				"rightArm2": {
					"rotation": {
						"0.0": [
							0,
							0,
							32.5
						],
						"0.1667": [
							0,
							0,
							32.5
						]
					}
				},
				"leftArm2": {
					"rotation": {
						"0.0": [
							5,
							0,
							-27.5
						],
						"0.1667": [
							5,
							0,
							-27.5
						]
					}
				},
				"head3": {
					"rotation": {
						"0.0": [
							37.5,
							0,
							0
						],
						"0.0833": [
							45,
							0,
							0
						],
						"0.1667": [
							37.5,
							0,
							0
						]
					},
					"position": {
						"0.0": [
							0,
							0,
							-1.4
						],
						"0.0833": [
							0,
							-1,
							-2.4
						],
						"0.1667": [
							0,
							0,
							-1.4
						]
					}
				},
				"rightLeg2": {
					"rotation": {
						"0.0": [
							5,
							0,
							10
						],
						"0.0833": [
							10,
							0,
							10
						],
						"0.1667": [
							5,
							0,
							10
						]
					}
				},
				"leftLeg2": {
					"rotation": {
						"0.0": [
							5,
							0,
							-7.5
						],
						"0.0833": [
							10,
							0,
							-7.5
						],
						"0.1667": [
							5,
							0,
							-7.5
						]
					}
				}
			},
			"particle_effects": {
				"0.0833": {
					"effect": "blood_hit",
					"locator": "blood"
				}
			}
		},
		"animation.plague_dog.attack": {
			"animation_length": 0.84,
			"bones": {
				"RightFoot": {
					"rotation": {
						"0.0": [
							12.5,
							0,
							0
						],
						"0.84": [
							12.5,
							0,
							0
						]
					}
				},
				"RightLeg": {
					"rotation": {
						"0.0": [
							52.5,
							0,
							0
						],
						"0.28": [
							43.74538,
							24.3683,
							5.7632
						],
						"0.52": [
							43.74538,
							24.3683,
							5.7632
						],
						"0.68": [
							52.5,
							0,
							0
						],
						"0.84": [
							52.5,
							0,
							0
						]
					}
				},
				"bone": {
					"rotation": {
						"0.0": [
							-50,
							0,
							0
						],
						"0.84": [
							-50,
							0,
							0
						]
					}
				},
				"bone2": {
					"rotation": {
						"0.0": [
							-15.12734,
							-2.3069,
							-1.27736
						],
						"0.84": [
							-15.12734,
							-2.3069,
							-1.27736
						]
					}
				},
				"hip": {
					"rotation": {
						"0.0": [
							-40,
							0,
							0
						],
						"0.84": [
							-40,
							0,
							0
						]
					}
				},
				"Abdomen": {
					"rotation": {
						"0.0": [
							-7.5,
							0,
							0
						],
						"0.28": [
							-9.08339,
							-19.69415,
							2.74666
						],
						"0.52": [
							-14.08339,
							-19.69415,
							2.74666
						],
						"0.68": [
							23.07781,
							24.77787,
							-4.31579
						],
						"0.84": [
							-7.5,
							0,
							0
						]
					}
				},
				"Chest": {
					"rotation": {
						"0.0": [
							-20,
							0,
							0
						],
						"0.28": [
							-19.5623,
							4.2453,
							11.76782
						],
						"0.52": [
							-24.57457,
							4.32784,
							11.28917
						],
						"0.68": [
							31.55382,
							-15.10835,
							0.18355
						],
						"0.84": [
							-20,
							0,
							0
						]
					}
				},
				"Tail": {
					"rotation": {
						"0.0": [
							7.5,
							0,
							0
						],
						"0.28": [
							50,
							0,
							0
						],
						"0.52": [
							57.5,
							0,
							0
						],
						"0.56": [
							50,
							0,
							0
						],
						"0.68": [
							20,
							0,
							0
						],
						"0.84": [
							7.5,
							0,
							0
						]
					}
				},
				"Tail2": {
					"rotation": {
						"0.0": [
							-15,
							0,
							0
						],
						"0.16": [
							-27.14,
							0,
							0
						],
						"0.28": [
							15,
							0,
							0
						],
						"0.56": [
							15,
							0,
							0
						],
						"0.64": [
							25,
							0,
							0
						],
						"0.68": [
							-5,
							0,
							0
						],
						"0.84": [
							-15,
							0,
							0
						]
					}
				},
				"RightHand": {
					"rotation": {
						"0.0": [
							45,
							0,
							0
						],
						"0.84": [
							45,
							0,
							0
						]
					}
				},
				"RightArm": {
					"rotation": {
						"0.0": [
							98.26511,
							-24.77164,
							-3.48303
						],
						"0.28": [
							130.76511,
							-24.77164,
							-3.48303
						],
						"0.84": [
							98.26511,
							-24.77164,
							-3.48303
						]
					}
				},
				"RightForeArm": {
					"rotation": {
						"0.0": [
							-77.5,
							0,
							0
						],
						"0.84": [
							-77.5,
							0,
							0
						]
					}
				},
				"Finger": {
					"rotation": {
						"0.0": [
							-52.12711,
							28.93057,
							20.61737
						],
						"0.84": [
							-52.12711,
							28.93057,
							20.61737
						]
					}
				},
				"Finger3": {
					"rotation": {
						"0.0": [
							0,
							-65,
							-32.5
						],
						"0.84": [
							0,
							-65,
							-32.5
						]
					}
				},
				"Finger2": {
					"rotation": {
						"0.0": [
							-72.5,
							0,
							0
						],
						"0.84": [
							-72.5,
							0,
							0
						]
					}
				},
				"Neck": {
					"rotation": {
						"0.0": [
							72.5,
							0,
							0
						],
						"0.28": [
							73.49629,
							5.90316,
							19.14314
						],
						"0.52": [
							73.49629,
							5.90316,
							19.14314
						],
						"0.68": [
							0.99629,
							5.90316,
							19.14314
						],
						"0.84": [
							72.5,
							0,
							0
						]
					}
				},
				"Head": {
					"rotation": {
						"0.0": [
							5,
							0,
							0
						],
						"0.28": [
							22.56639,
							-3.664,
							-16.12838
						],
						"0.56": [
							22.56639,
							-3.664,
							-16.12838
						],
						"0.68": [
							0.63248,
							-12.88292,
							-20.04811
						],
						"0.84": [
							5,
							0,
							0
						]
					}
				},
				"Head2": {
					"rotation": {
						"0.0": [
							10.22343,
							-0.20442,
							0.74892
						],
						"0.28": [
							40.22343,
							-0.20442,
							0.74892
						],
						"0.4": [
							47.72343,
							-0.20442,
							0.74892
						],
						"0.52": [
							40.22343,
							-0.20442,
							0.74892
						],
						"0.68": [
							-1.88344,
							0.55851,
							-5.24242
						],
						"0.84": [
							10.22343,
							-0.20442,
							0.74892
						]
					}
				},
				"eitherEar": {
					"rotation": {
						"0.0": [
							-11.70092,
							19.3546,
							-32.00206
						],
						"0.84": [
							-11.70092,
							19.3546,
							-32.00206
						]
					}
				},
				"LeftArm": {
					"rotation": {
						"0.0": [
							79.52521,
							17.22575,
							-3.13388
						],
						"0.84": [
							79.52521,
							17.22575,
							-3.13388
						]
					}
				},
				"LeftForeArm": {
					"rotation": {
						"0.0": [
							-60,
							0,
							0
						],
						"0.84": [
							-60,
							0,
							0
						]
					}
				},
				"LeftHand": {
					"rotation": {
						"0.0": [
							37.5,
							0,
							0
						],
						"0.84": [
							37.5,
							0,
							0
						]
					}
				},
				"Finger4": {
					"rotation": {
						"0.0": [
							-35,
							0,
							-20
						],
						"0.84": [
							-35,
							0,
							-20
						]
					}
				},
				"Finger5": {
					"rotation": {
						"0.0": [
							-50,
							0,
							0
						],
						"0.84": [
							-50,
							0,
							0
						]
					}
				},
				"Finger6": {
					"rotation": {
						"0.0": [
							-17.5,
							50,
							32.5
						],
						"0.84": [
							-17.5,
							50,
							32.5
						]
					}
				},
				"eitherEar2": {
					"rotation": {
						"0.0": [
							0,
							0,
							25
						],
						"0.84": [
							0,
							0,
							25
						]
					}
				},
				"language": {
					"rotation": {
						"0.0": [
							14.48557,
							-3.1004,
							0.45036
						],
						"0.28": [
							21.98557,
							-3.1004,
							0.45036
						],
						"0.52": [
							24.48557,
							-3.1004,
							0.45036
						],
						"0.68": [
							4.48557,
							-3.1004,
							0.45036
						],
						"0.84": [
							14.48557,
							-3.1004,
							0.45036
						]
					}
				},
				"language2": {
					"rotation": {
						"0.0": [
							-7.5,
							0,
							0
						],
						"0.84": [
							-7.5,
							0,
							0
						]
					}
				},
				"All": {
					"rotation": {
						"0.0": [
							0,
							0,
							0
						],
						"0.28": [
							0,
							10,
							0
						],
						"0.52": [
							0,
							10,
							0
						],
						"0.72": [
							0,
							2.5,
							0
						],
						"0.84": [
							0,
							0,
							0
						]
					}
				},
				"outcast": {
					"position": [
						0,
						-100,
						7
					],
					"scale": 0
				}
			}
		},
		"animation.plague_dog.head": {
			"loop": true,
			"bones": {
				"Head": {
					"scale": 1.5
				}
			}
		},
		"animation.plague_dog.outcast_scale_one": {
			"loop": true,
			"bones": {
				"outcast": {
					"position": [
						1,
						-4,
						-3
					],
					"scale": 0.75
				}
			}
		},
		"animation.plague_dog.outcast_scale_two": {
			"loop": true,
			"bones": {
				"outcast": {
					"position": [
						1,
						-8,
						-7
					],
					"scale": 0.5
				}
			}
		}
	}
}