{
	"format_version": "1.12.0",
	"minecraft:geometry": [
		{
			"description": {
				"identifier": "geometry.plague",
				"texture_width": 128,
				"texture_height": 128,
				"visible_bounds_width": 6,
				"visible_bounds_height": 5.5,
				"visible_bounds_offset": [
					0,
					2.25,
					0
				]
			},
			"bones": [
				{
					"name": "waist",
					"pivot": [
						0,
						0,
						0
					]
				},
				{
					"name": "Hip",
					"parent": "waist",
					"pivot": [
						0,
						26,
						4
					],
					"cubes": [
						{
							"origin": [
								-7,
								25,
								1
							],
							"size": [
								14,
								4,
								6
							],
							"uv": [
								46,
								0
							]
						}
					]
				},
				{
					"name": "Tail",
					"parent": "Hip",
					"pivot": [
						0,
						27,
						7
					],
					"cubes": [
						{
							"origin": [
								-2,
								25,
								7
							],
							"size": [
								4,
								4,
								10
							],
							"uv": [
								76,
								0
							]
						}
					]
				},
				{
					"name": "Tail2",
					"parent": "Tail",
					"pivot": [
						0,
						27.5,
						17
					],
					"cubes": [
						{
							"origin": [
								-1.5,
								26,
								17
							],
							"size": [
								3,
								3,
								8
							],
							"uv": [
								16,
								89
							]
						}
					]
				},
				{
					"name": "Tail3",
					"parent": "Tail2",
					"pivot": [
						0,
						28,
						25
					],
					"cubes": [
						{
							"origin": [
								-1,
								27,
								25
							],
							"size": [
								2,
								2,
								10
							],
							"uv": [
								78,
								84
							]
						}
					]
				},
				{
					"name": "bone",
					"parent": "Hip",
					"pivot": [
						0,
						29,
						4
					],
					"cubes": [
						{
							"origin": [
								-5,
								29,
								1
							],
							"size": [
								10,
								8,
								6
							],
							"uv": [
								56,
								79
							]
						},
						{
							"origin": [
								0,
								29,
								7
							],
							"size": [
								0,
								8,
								3
							],
							"uv": [
								0,
								18
							]
						}
					]
				},
				{
					"name": "Chest",
					"parent": "bone",
					"pivot": [
						0,
						37,
						4
					],
					"cubes": [
						{
							"origin": [
								-9,
								36,
								-2
							],
							"size": [
								18,
								11,
								10
							],
							"uv": [
								0,
								21
							]
						},
						{
							"origin": [
								0,
								47,
								6
							],
							"size": [
								0,
								4,
								4
							],
							"uv": [
								0,
								2
							]
						},
						{
							"origin": [
								-12,
								43,
								1
							],
							"size": [
								6,
								6,
								6
							],
							"uv": [
								86,
								34
							]
						},
						{
							"origin": [
								6,
								43,
								1
							],
							"size": [
								6,
								6,
								6
							],
							"uv": [
								86,
								34
							]
						},
						{
							"origin": [
								0,
								36,
								8
							],
							"size": [
								0,
								11,
								2
							],
							"uv": [
								56,
								29
							]
						}
					]
				},
				{
					"name": "Neck",
					"parent": "Chest",
					"pivot": [
						0,
						46.5,
						3
					],
					"cubes": [
						{
							"origin": [
								-3.5,
								47,
								0
							],
							"size": [
								7,
								5,
								6
							],
							"uv": [
								82,
								73
							]
						}
					]
				},
				{
					"name": "head",
					"parent": "Neck",
					"pivot": [
						0,
						53.95,
						2.8
					],
					"cubes": [
						{
							"origin": [
								-4,
								51,
								-1
							],
							"size": [
								8,
								8,
								8
							],
							"uv": [
								26,
								60
							]
						},
						{
							"origin": [
								-4,
								51,
								-1
							],
							"size": [
								8,
								8,
								8
							],
							"inflate": 0.2,
							"uv": [
								48,
								13
							]
						},
						{
							"origin": [
								-2.5,
								51.75,
								-7
							],
							"size": [
								5,
								5,
								6
							],
							"uv": [
								96,
								90
							]
						},
						{
							"origin": [
								-2.5,
								51.75,
								-7
							],
							"size": [
								5,
								5,
								6
							],
							"inflate": 0.2,
							"uv": [
								71,
								96
							]
						},
						{
							"origin": [
								-2.5,
								50.75,
								-7
							],
							"size": [
								5,
								1,
								6
							],
							"uv": [
								103,
								101
							]
						}
					]
				},
				{
					"name": "Horn",
					"parent": "head",
					"pivot": [
						3.5,
						57,
						3.5
					],
					"rotation": [
						0,
						20,
						7.5
					],
					"cubes": [
						{
							"origin": [
								3,
								55.5,
								2
							],
							"size": [
								7,
								3,
								3
							],
							"uv": [
								105,
								46
							]
						},
						{
							"origin": [
								6,
								55.5,
								2
							],
							"size": [
								2,
								3,
								3
							],
							"inflate": 0.2,
							"uv": [
								0,
								0
							]
						}
					]
				},
				{
					"name": "Horn2",
					"parent": "Horn",
					"pivot": [
						9.5,
						57,
						3.5
					],
					"rotation": [
						0,
						42.5,
						-10
					],
					"cubes": [
						{
							"origin": [
								10,
								56,
								2.5
							],
							"size": [
								7,
								2,
								2
							],
							"uv": [
								86,
								46
							]
						},
						{
							"origin": [
								12,
								56,
								2.5
							],
							"size": [
								4,
								2,
								2
							],
							"inflate": 0.2,
							"uv": [
								18,
								85
							]
						}
					]
				},
				{
					"name": "Horn3",
					"parent": "Horn2",
					"pivot": [
						17,
						57,
						3.5
					],
					"rotation": [
						0,
						25,
						-35
					],
					"cubes": [
						{
							"origin": [
								17,
								56.5,
								3
							],
							"size": [
								4,
								1,
								1
							],
							"uv": [
								0,
								29
							]
						}
					]
				},
				{
					"name": "Horn4",
					"parent": "head",
					"pivot": [
						-3.5,
						57,
						3.5
					],
					"rotation": [
						0,
						-20,
						-7.5
					],
					"cubes": [
						{
							"origin": [
								-10,
								55.5,
								2
							],
							"size": [
								7,
								3,
								3
							],
							"uv": [
								105,
								46
							],
							"mirror": true
						},
						{
							"origin": [
								-8,
								55.5,
								2
							],
							"size": [
								1,
								3,
								3
							],
							"inflate": 0.2,
							"uv": [
								13,
								118
							],
							"mirror": true
						}
					]
				},
				{
					"name": "Horn5",
					"parent": "Horn4",
					"pivot": [
						-9.5,
						57,
						3.5
					],
					"rotation": [
						0,
						-42.5,
						10
					],
					"cubes": [
						{
							"origin": [
								-17,
								56,
								2.5
							],
							"size": [
								7,
								2,
								2
							],
							"uv": [
								86,
								46
							],
							"mirror": true
						},
						{
							"origin": [
								-16,
								56,
								2.5
							],
							"size": [
								4,
								2,
								2
							],
							"inflate": 0.2,
							"uv": [
								0,
								114
							],
							"mirror": true
						}
					]
				},
				{
					"name": "Horn6",
					"parent": "Horn5",
					"pivot": [
						-17,
						57,
						3.5
					],
					"rotation": [
						0,
						-25,
						35
					],
					"cubes": [
						{
							"origin": [
								-21,
								56.5,
								3
							],
							"size": [
								4,
								1,
								1
							],
							"uv": [
								0,
								29
							],
							"mirror": true
						}
					]
				},
				{
					"name": "Right_Arm",
					"parent": "Chest",
					"pivot": [
						-9,
						44.33333,
						3.83333
					],
					"cubes": [
						{
							"origin": [
								-13.5,
								32,
								0.5
							],
							"size": [
								7,
								14,
								7
							],
							"uv": [
								83,
								107
							]
						},
						{
							"origin": [
								-13.5,
								30,
								0.5
							],
							"size": [
								7,
								14,
								7
							],
							"inflate": 0.2,
							"uv": [
								18,
								0
							]
						},
						{
							"origin": [
								-10,
								33,
								7.5
							],
							"size": [
								0,
								14,
								3
							],
							"uv": [
								48,
								104
							]
						}
					]
				},
				{
					"name": "right_forearm",
					"parent": "Right_Arm",
					"pivot": [
						-10,
						31.5,
						4
					],
					"cubes": [
						{
							"origin": [
								-13.5,
								23,
								0
							],
							"size": [
								7,
								9,
								8
							],
							"uv": [
								0,
								68
							]
						},
						{
							"origin": [
								-13,
								18,
								0.5
							],
							"size": [
								6,
								5,
								7
							],
							"uv": [
								79,
								22
							]
						}
					]
				},
				{
					"name": "hand",
					"parent": "right_forearm",
					"pivot": [
						-10,
						18.5,
						4
					],
					"cubes": [
						{
							"origin": [
								-12.5,
								13,
								1.5
							],
							"size": [
								5,
								5,
								5
							],
							"uv": [
								102,
								64
							]
						}
					]
				},
				{
					"name": "Sword",
					"parent": "hand",
					"pivot": [
						-10,
						15,
						4
					],
					"cubes": [
						{
							"origin": [
								-11,
								14,
								1
							],
							"size": [
								2,
								2,
								8
							],
							"uv": [
								94,
								0
							]
						},
						{
							"origin": [
								-11.5,
								13.5,
								7.5
							],
							"size": [
								3,
								3,
								3
							],
							"pivot": [
								-10,
								15,
								9.5
							],
							"rotation": [
								0,
								0,
								50
							],
							"uv": [
								68,
								50
							]
						},
						{
							"origin": [
								-11.5,
								13.5,
								13.5
							],
							"size": [
								3,
								3,
								3
							],
							"pivot": [
								-10,
								15,
								9.5
							],
							"rotation": [
								0,
								0,
								50
							],
							"uv": [
								68,
								50
							]
						},
						{
							"origin": [
								-10.5,
								14.5,
								16.5
							],
							"size": [
								1,
								1,
								1
							],
							"uv": [
								6,
								21
							]
						},
						{
							"origin": [
								-11.5,
								13.5,
								10.5
							],
							"size": [
								3,
								3,
								3
							],
							"uv": [
								68,
								50
							]
						},
						{
							"origin": [
								-11,
								13.5,
								-2
							],
							"size": [
								2,
								3,
								3
							],
							"uv": [
								40,
								97
							]
						}
					]
				},
				{
					"name": "bone2",
					"parent": "Sword",
					"pivot": [
						-10,
						15,
						0.5
					],
					"rotation": [
						7.5,
						0,
						0
					],
					"cubes": [
						{
							"origin": [
								-10.5,
								13,
								-7.5
							],
							"size": [
								1,
								4,
								8
							],
							"uv": [
								100,
								76
							]
						},
						{
							"origin": [
								-10,
								17,
								-7.5
							],
							"size": [
								0,
								2,
								8
							],
							"uv": [
								56,
								3
							]
						},
						{
							"origin": [
								-10,
								12,
								-7.5
							],
							"size": [
								0,
								1,
								8
							],
							"uv": [
								0,
								58
							]
						}
					]
				},
				{
					"name": "bone3",
					"parent": "bone2",
					"pivot": [
						-10,
						15,
						-7.5
					],
					"rotation": [
						-10,
						0,
						0
					],
					"cubes": [
						{
							"origin": [
								-10.5,
								13,
								-15.5
							],
							"size": [
								1,
								4,
								8
							],
							"uv": [
								100,
								76
							]
						},
						{
							"origin": [
								-10,
								17,
								-15.5
							],
							"size": [
								0,
								1,
								8
							],
							"uv": [
								18,
								57
							]
						},
						{
							"origin": [
								-10,
								11,
								-15.5
							],
							"size": [
								0,
								2,
								9
							],
							"uv": [
								0,
								55
							]
						}
					]
				},
				{
					"name": "bone4",
					"parent": "bone3",
					"pivot": [
						-10,
						15,
						-15.5
					],
					"rotation": [
						-5,
						0,
						0
					],
					"cubes": [
						{
							"origin": [
								-10.5,
								13,
								-23.5
							],
							"size": [
								1,
								4,
								8
							],
							"uv": [
								100,
								76
							]
						},
						{
							"origin": [
								-10,
								17,
								-23.5
							],
							"size": [
								0,
								2,
								8
							],
							"uv": [
								26,
								40
							]
						},
						{
							"origin": [
								-10,
								12,
								-23.5
							],
							"size": [
								0,
								1,
								9
							],
							"uv": [
								56,
								1
							]
						}
					]
				},
				{
					"name": "bone5",
					"parent": "bone4",
					"pivot": [
						-10,
						15,
						-23.5
					],
					"rotation": [
						-10,
						0,
						0
					],
					"cubes": [
						{
							"origin": [
								-10.5,
								13,
								-31.5
							],
							"size": [
								1,
								4,
								8
							],
							"uv": [
								100,
								76
							]
						},
						{
							"origin": [
								-10.5,
								13.5,
								-37.5
							],
							"size": [
								1,
								3,
								6
							],
							"uv": [
								20,
								103
							]
						},
						{
							"origin": [
								-10,
								17,
								-31.5
							],
							"size": [
								0,
								1,
								8
							],
							"uv": [
								18,
								56
							]
						},
						{
							"origin": [
								-10,
								11,
								-31.5
							],
							"size": [
								0,
								2,
								9
							],
							"uv": [
								46,
								20
							]
						},
						{
							"origin": [
								-10,
								2.75,
								-38.5
							],
							"size": [
								0,
								16,
								8
							],
							"pivot": [
								-10,
								15,
								-33.5
							],
							"rotation": [
								-25,
								0,
								0
							],
							"uv": [
								66,
								104
							]
						}
					]
				},
				{
					"name": "Left_Arm",
					"parent": "Chest",
					"pivot": [
						9,
						44.33333,
						3.83333
					],
					"cubes": [
						{
							"origin": [
								6.5,
								32,
								0.5
							],
							"size": [
								7,
								14,
								7
							],
							"uv": [
								83,
								107
							],
							"mirror": true
						},
						{
							"origin": [
								6.5,
								34,
								0.5
							],
							"size": [
								7,
								14,
								7
							],
							"inflate": 0.2,
							"uv": [
								18,
								0
							],
							"mirror": true
						},
						{
							"origin": [
								10,
								33,
								7.5
							],
							"size": [
								0,
								14,
								3
							],
							"uv": [
								48,
								104
							],
							"mirror": true
						}
					]
				},
				{
					"name": "left_forearm",
					"parent": "Left_Arm",
					"pivot": [
						10,
						31.5,
						4
					],
					"cubes": [
						{
							"origin": [
								6.5,
								23,
								0
							],
							"size": [
								7,
								9,
								8
							],
							"uv": [
								0,
								68
							],
							"mirror": true
						},
						{
							"origin": [
								7,
								18,
								0.5
							],
							"size": [
								6,
								5,
								7
							],
							"uv": [
								79,
								22
							],
							"mirror": true
						}
					]
				},
				{
					"name": "hand2",
					"parent": "left_forearm",
					"pivot": [
						10,
						18.5,
						4
					],
					"cubes": [
						{
							"origin": [
								7.5,
								13,
								1.5
							],
							"size": [
								5,
								5,
								5
							],
							"uv": [
								102,
								64
							],
							"mirror": true
						}
					]
				},
				{
					"name": "Sword2",
					"parent": "hand2",
					"pivot": [
						10,
						15,
						4
					],
					"cubes": [
						{
							"origin": [
								9,
								14,
								1
							],
							"size": [
								2,
								2,
								8
							],
							"uv": [
								94,
								0
							],
							"mirror": true
						},
						{
							"origin": [
								8.5,
								13.5,
								7.5
							],
							"size": [
								3,
								3,
								3
							],
							"pivot": [
								10,
								15,
								9.5
							],
							"rotation": [
								0,
								0,
								-50
							],
							"uv": [
								68,
								50
							],
							"mirror": true
						},
						{
							"origin": [
								8.5,
								13.5,
								13.5
							],
							"size": [
								3,
								3,
								3
							],
							"pivot": [
								10,
								15,
								9.5
							],
							"rotation": [
								0,
								0,
								-50
							],
							"uv": [
								68,
								50
							],
							"mirror": true
						},
						{
							"origin": [
								9.5,
								14.5,
								16.5
							],
							"size": [
								1,
								1,
								1
							],
							"uv": [
								6,
								21
							],
							"mirror": true
						},
						{
							"origin": [
								8.5,
								13.5,
								10.5
							],
							"size": [
								3,
								3,
								3
							],
							"uv": [
								68,
								50
							],
							"mirror": true
						},
						{
							"origin": [
								9,
								13.5,
								-2
							],
							"size": [
								2,
								3,
								3
							],
							"uv": [
								40,
								97
							],
							"mirror": true
						}
					]
				},
				{
					"name": "bone6",
					"parent": "Sword2",
					"pivot": [
						10,
						15,
						0.5
					],
					"rotation": [
						7.5,
						0,
						0
					],
					"cubes": [
						{
							"origin": [
								9.5,
								13,
								-7.5
							],
							"size": [
								1,
								4,
								8
							],
							"uv": [
								100,
								76
							],
							"mirror": true
						},
						{
							"origin": [
								10,
								17,
								-7.5
							],
							"size": [
								0,
								2,
								8
							],
							"uv": [
								56,
								3
							],
							"mirror": true
						},
						{
							"origin": [
								10,
								12,
								-7.5
							],
							"size": [
								0,
								1,
								8
							],
							"uv": [
								0,
								58
							],
							"mirror": true
						}
					]
				},
				{
					"name": "bone7",
					"parent": "bone6",
					"pivot": [
						10,
						15,
						-7.5
					],
					"rotation": [
						-10,
						0,
						0
					],
					"cubes": [
						{
							"origin": [
								9.5,
								13,
								-15.5
							],
							"size": [
								1,
								4,
								8
							],
							"uv": [
								100,
								76
							],
							"mirror": true
						},
						{
							"origin": [
								10,
								17,
								-15.5
							],
							"size": [
								0,
								1,
								8
							],
							"uv": [
								18,
								57
							],
							"mirror": true
						},
						{
							"origin": [
								10,
								11,
								-15.5
							],
							"size": [
								0,
								2,
								9
							],
							"uv": [
								0,
								55
							],
							"mirror": true
						}
					]
				},
				{
					"name": "bone8",
					"parent": "bone7",
					"pivot": [
						10,
						15,
						-15.5
					],
					"rotation": [
						-5,
						0,
						0
					],
					"cubes": [
						{
							"origin": [
								9.5,
								13,
								-23.5
							],
							"size": [
								1,
								4,
								8
							],
							"uv": [
								100,
								76
							],
							"mirror": true
						},
						{
							"origin": [
								10,
								17,
								-23.5
							],
							"size": [
								0,
								2,
								8
							],
							"uv": [
								26,
								40
							],
							"mirror": true
						},
						{
							"origin": [
								10,
								12,
								-23.5
							],
							"size": [
								0,
								1,
								9
							],
							"uv": [
								56,
								1
							],
							"mirror": true
						}
					]
				},
				{
					"name": "bone9",
					"parent": "bone8",
					"pivot": [
						10,
						15,
						-23.5
					],
					"rotation": [
						-10,
						0,
						0
					],
					"cubes": [
						{
							"origin": [
								9.5,
								13,
								-31.5
							],
							"size": [
								1,
								4,
								8
							],
							"uv": [
								100,
								76
							],
							"mirror": true
						},
						{
							"origin": [
								9.5,
								13.5,
								-37.5
							],
							"size": [
								1,
								3,
								6
							],
							"uv": [
								20,
								103
							],
							"mirror": true
						},
						{
							"origin": [
								10,
								17,
								-31.5
							],
							"size": [
								0,
								1,
								8
							],
							"uv": [
								18,
								56
							],
							"mirror": true
						},
						{
							"origin": [
								10,
								11,
								-31.5
							],
							"size": [
								0,
								2,
								9
							],
							"uv": [
								46,
								20
							],
							"mirror": true
						},
						{
							"origin": [
								10,
								2.75,
								-38.5
							],
							"size": [
								0,
								16,
								8
							],
							"pivot": [
								10,
								15,
								-33.5
							],
							"rotation": [
								-25,
								0,
								0
							],
							"uv": [
								66,
								104
							],
							"mirror": true
						}
					]
				},
				{
					"name": "Right_Leg",
					"parent": "waist",
					"pivot": [
						-4,
						26.5,
						4
					],
					"cubes": [
						{
							"origin": [
								-7.5,
								15,
								0.5
							],
							"size": [
								7,
								12,
								7
							],
							"uv": [
								58,
								60
							]
						}
					]
				},
				{
					"name": "right_calf",
					"parent": "Right_Leg",
					"pivot": [
						-4,
						16,
						4
					],
					"cubes": [
						{
							"origin": [
								-6,
								2,
								1.5
							],
							"size": [
								4,
								5,
								4
							],
							"uv": [
								86,
								64
							]
						},
						{
							"origin": [
								-6.5,
								7,
								1.5
							],
							"size": [
								5,
								9,
								5
							],
							"uv": [
								51,
								93
							]
						}
					]
				},
				{
					"name": "Foot",
					"parent": "right_calf",
					"pivot": [
						-4,
						3,
						3.5
					],
					"cubes": [
						{
							"origin": [
								-6.5,
								0,
								1
							],
							"size": [
								5,
								4,
								5
							],
							"uv": [
								104,
								29
							]
						}
					]
				},
				{
					"name": "Finger",
					"parent": "Foot",
					"pivot": [
						-5,
						1.5,
						1.25
					],
					"cubes": [
						{
							"origin": [
								-6,
								0.5,
								-2.75
							],
							"size": [
								2,
								2,
								4
							],
							"uv": [
								54,
								107
							]
						},
						{
							"origin": [
								-5,
								0,
								-4.5
							],
							"size": [
								0,
								3,
								4
							],
							"uv": [
								0,
								66
							]
						}
					]
				},
				{
					"name": "Finger4",
					"parent": "Foot",
					"pivot": [
						-4,
						1.5,
						5.25
					],
					"cubes": [
						{
							"origin": [
								-5,
								0.5,
								5.25
							],
							"size": [
								2,
								2,
								4
							],
							"uv": [
								54,
								107
							]
						},
						{
							"origin": [
								-4,
								0,
								6.5
							],
							"size": [
								0,
								3,
								4
							],
							"uv": [
								0,
								63
							]
						}
					]
				},
				{
					"name": "Finger2",
					"parent": "Foot",
					"pivot": [
						-4,
						1.5,
						1.25
					],
					"cubes": [
						{
							"origin": [
								-5,
								0.5,
								-2.75
							],
							"size": [
								2,
								2,
								4
							],
							"uv": [
								95,
								101
							]
						},
						{
							"origin": [
								-4,
								0,
								-4.5
							],
							"size": [
								0,
								3,
								4
							],
							"uv": [
								0,
								66
							]
						}
					]
				},
				{
					"name": "Finger3",
					"parent": "Foot",
					"pivot": [
						-3,
						1.5,
						1.25
					],
					"cubes": [
						{
							"origin": [
								-4,
								0.5,
								-2.75
							],
							"size": [
								2,
								2,
								4
							],
							"uv": [
								54,
								107
							]
						},
						{
							"origin": [
								-3,
								0,
								-4.5
							],
							"size": [
								0,
								3,
								4
							],
							"uv": [
								0,
								66
							]
						}
					]
				},
				{
					"name": "Clothing",
					"parent": "Right_Leg",
					"pivot": [
						-2,
						28.25,
						4
					],
					"cubes": [
						{
							"origin": [
								-8,
								19.25,
								0
							],
							"size": [
								9,
								10,
								8
							],
							"uv": [
								34,
								42
							]
						}
					]
				},
				{
					"name": "Clothing2",
					"parent": "Clothing",
					"pivot": [
						-4.5,
						20.25,
						4
					],
					"cubes": [
						{
							"origin": [
								-8,
								6.25,
								0
							],
							"size": [
								9,
								14,
								8
							],
							"uv": [
								0,
								42
							]
						}
					]
				},
				{
					"name": "Left_Leg",
					"parent": "waist",
					"pivot": [
						4,
						26.5,
						4
					],
					"cubes": [
						{
							"origin": [
								0.5,
								15,
								0.5
							],
							"size": [
								7,
								12,
								7
							],
							"uv": [
								58,
								60
							],
							"mirror": true
						}
					]
				},
				{
					"name": "left_calf",
					"parent": "Left_Leg",
					"pivot": [
						4,
						16,
						4
					],
					"cubes": [
						{
							"origin": [
								2,
								2,
								1.5
							],
							"size": [
								4,
								5,
								4
							],
							"uv": [
								86,
								64
							],
							"mirror": true
						},
						{
							"origin": [
								1.5,
								7,
								1.5
							],
							"size": [
								5,
								9,
								5
							],
							"uv": [
								51,
								93
							],
							"mirror": true
						}
					]
				},
				{
					"name": "Foot2",
					"parent": "left_calf",
					"pivot": [
						4,
						3,
						3.5
					],
					"cubes": [
						{
							"origin": [
								1.5,
								0,
								1
							],
							"size": [
								5,
								4,
								5
							],
							"uv": [
								104,
								29
							],
							"mirror": true
						}
					]
				},
				{
					"name": "Finger5",
					"parent": "Foot2",
					"pivot": [
						5,
						1.5,
						1.25
					],
					"cubes": [
						{
							"origin": [
								4,
								0.5,
								-2.75
							],
							"size": [
								2,
								2,
								4
							],
							"uv": [
								54,
								107
							],
							"mirror": true
						},
						{
							"origin": [
								5,
								0,
								-4.5
							],
							"size": [
								0,
								3,
								4
							],
							"uv": [
								0,
								66
							],
							"mirror": true
						}
					]
				},
				{
					"name": "Finger6",
					"parent": "Foot2",
					"pivot": [
						4,
						1.5,
						5.25
					],
					"cubes": [
						{
							"origin": [
								3,
								0.5,
								5.25
							],
							"size": [
								2,
								2,
								4
							],
							"uv": [
								54,
								107
							],
							"mirror": true
						},
						{
							"origin": [
								4,
								0,
								6.5
							],
							"size": [
								0,
								3,
								4
							],
							"uv": [
								0,
								63
							],
							"mirror": true
						}
					]
				},
				{
					"name": "Finger7",
					"parent": "Foot2",
					"pivot": [
						4,
						1.5,
						1.25
					],
					"cubes": [
						{
							"origin": [
								3,
								0.5,
								-2.75
							],
							"size": [
								2,
								2,
								4
							],
							"uv": [
								95,
								101
							],
							"mirror": true
						},
						{
							"origin": [
								4,
								0,
								-4.5
							],
							"size": [
								0,
								3,
								4
							],
							"uv": [
								0,
								66
							],
							"mirror": true
						}
					]
				},
				{
					"name": "Finger8",
					"parent": "Foot2",
					"pivot": [
						3,
						1.5,
						1.25
					],
					"cubes": [
						{
							"origin": [
								2,
								0.5,
								-2.75
							],
							"size": [
								2,
								2,
								4
							],
							"uv": [
								54,
								107
							],
							"mirror": true
						},
						{
							"origin": [
								3,
								0,
								-4.5
							],
							"size": [
								0,
								3,
								4
							],
							"uv": [
								0,
								66
							],
							"mirror": true
						}
					]
				},
				{
					"name": "Clothing3",
					"parent": "Left_Leg",
					"pivot": [
						2,
						28.25,
						4
					],
					"cubes": [
						{
							"origin": [
								-1,
								19.25,
								0
							],
							"size": [
								9,
								10,
								8
							],
							"uv": [
								34,
								42
							],
							"mirror": true
						}
					]
				},
				{
					"name": "Clothing4",
					"parent": "Clothing3",
					"pivot": [
						4.5,
						20.25,
						4
					],
					"cubes": [
						{
							"origin": [
								-1,
								6.25,
								0
							],
							"size": [
								9,
								14,
								8
							],
							"uv": [
								0,
								42
							],
							"mirror": true
						}
					]
				}
			]
		}
	]
}